[
    {
        "name": "Classical",
        "creator": "SecRifal",
        "verifier": "SecRifal",
        "levelID": 16,
        "stars": 50,
        "verifURL": "https://youtu.be/YE2mEpY9aCM",
        "difficulty": "Insane",
        "skillset": "memory-silver; ufo-gold; ball-gold",
        "desc": "Just a classic level? Practice Recomended!"
    },
    {
        "name": "Find Me",
        "creator": "T3Ynka",
        "verifier": "T3Ynka",
        "levelID": 41,
        "stars": 45,
        "verifURL": "https://youtu.be/f_qYnfDz9tk",
        "difficulty": "Insane",
        "skillset": "timings-gold; ship-gold; disbalance-diamond",
        "desc": false
    },
    {
        "name": "CyberShapes",
        "creator": "HydraShape",
        "verifier": "HydraShape",
        "levelID": 32,
        "stars": 43,
        "verifURL": "https://youtu.be/N7EwLnmLz8c",
        "difficulty": "Hard",
        "skillset": "robot-gold; timings-gold; disbalance-silver",
        "desc": false
    },
    {
        "name": "Black Step",
        "creator": "T3Ynka",
        "verifier": "T3Ynka",
        "levelID": 37,
        "stars": 41,
        "verifURL": "https://youtu.be/RtPxntQM4Tw",
        "difficulty": "Hard",
        "skillset": "memory-silver; cube-gold; disbalance-gold",
        "desc": "419 att"
    },
    {
        "name": "Bankomat",
        "creator": "SecRifal",
        "verifier": "SecRifal",
        "levelID": 18,
        "stars": 40,
        "verifURL": "https://youtu.be/oiDzOnQmsDQ",
        "difficulty": "Hard",
        "skillset": "robot-silver; timings-gold; disbalance-gold",
        "desc": "One of my favorite songs ."
    },
    {
        "name": "He Sees Everything",
        "creator": "Krictor",
        "verifier": "Krictor",
        "levelID": 3,
        "stars": 25,
        "verifURL": false,
        "difficulty": "Medium",
        "skillset": "memory-gold; timings-silver; disbalance-silver",
        "desc": false
    },
    {
        "name": "Megalovania",
        "creator": "SecRifal",
        "verifier": "SecRifal",
        "levelID": 20,
        "stars": 15,
        "verifURL": false,
        "difficulty": "Medium",
        "skillset": "wave-silver; ufo-silver; speed-diamond",
        "desc": "Good luck)"
    },
    {
        "name": "Giena",
        "creator": "Solozar",
        "verifier": "Solozar",
        "levelID": 52,
        "stars": 10,
        "verifURL": false,
        "difficulty": "Easy",
        "skillset": "timings-silver; wave-silver; disbalance-silver",
        "desc": "by solozar"
    }
]

